CHANGES
LICENSE
MANIFEST.in
README.rst
manage.py
setup.cfg
setup.py
tox.ini
docs/conf.py
docs/globals.txt
docs/index.rst
docs/install.rst
docs/_ext/djangodocs.py
docs/_ext/github.py
docs/_ext/version.py
src/drf_dynamic_serializer.egg-info/PKG-INFO
src/drf_dynamic_serializer.egg-info/SOURCES.txt
src/drf_dynamic_serializer.egg-info/dependency_links.txt
src/drf_dynamic_serializer.egg-info/requires.txt
src/drf_dynamic_serializer.egg-info/top_level.txt
src/dynamic_serializer/__init__.py
src/dynamic_serializer/core.py
src/requirements/install.pip
src/requirements/testing.pip