Metadata-Version: 2.1
Name: drf-dynamic-serializer
Version: 1.2.0
Summary: DjangoRestFramework Dynamic Serializer
Home-page: https://github.com/saxix/drf-dynamic-serializer
Author: Stefano Apostolico
Author-email: s.apostolico@gmail.com
License: MIT
Platform: linux
Classifier: Environment :: Web Environment
Classifier: Framework :: Django
Classifier: Framework :: Django :: 1.9
Classifier: Framework :: Django :: 1.10
Classifier: Framework :: Django :: 1.11
Classifier: Operating System :: OS Independent
Classifier: Programming Language :: Python :: 2.7
Classifier: Programming Language :: Python :: 3.4
Classifier: Programming Language :: Python :: 3.5
Classifier: Programming Language :: Python :: 3.6
Classifier: Intended Audience :: Developers
Provides-Extra: tests
